Metadata-Version: 1.0
Name: proxapy
Version: 0.1.4
Summary: Simple API proxy that uses Flask/requests/gunicorn.
Home-page: http://github.com/enricobacis/proxapy
Author: Enrico Bacis
Author-email: enrico.bacis@gmail.com
License: MIT
Keywords: api proxy server flask requests gunicorn
Platform: UNKNOWN
